{"name":"Cambio_clave_CP0018M_SYS_Realizar el cambio de clave para un usuario BMO.","id":"cambio-de-clave;cambio-clave-cp0018m-sys-realizar-el-cambio-de-clave-para-un-usuario-bmo.","testSteps":[{"number":1,"description":"Example #1: {tipoId\u003d\"CC\", usuario\u003d\"999730\", contrasena\u003d\"1112\", newPass\u003d\"1113\", subtipo\u003d\"BMO\"}","duration":353649,"startTime":"2024-09-04T11:23:50.074-05:00[America/Bogota]","result":"SUCCESS","precondition":false,"children":[{"number":2,"description":"And ingreso al aplicativo","duration":42372,"startTime":"2024-09-04T11:23:56.859-05:00[America/Bogota]","result":"SUCCESS","precondition":false,"children":[{"number":3,"description":"Log in to the application","duration":41945,"startTime":"2024-09-04T11:23:57.270-05:00[America/Bogota]","result":"SUCCESS","precondition":false}]},{"number":4,"description":"And verifico la version del aplicativo","duration":28137,"startTime":"2024-09-04T11:24:39.232-05:00[America/Bogota]","result":"SUCCESS","precondition":false,"children":[{"number":5,"description":"Check version","duration":28125,"startTime":"2024-09-04T11:24:39.238-05:00[America/Bogota]","result":"SUCCESS","precondition":false}]},{"number":6,"description":"When ingreso las credenciales \"CC\" \"999730\" \"1112\"","duration":88287,"startTime":"2024-09-04T11:25:07.370-05:00[America/Bogota]","result":"SUCCESS","precondition":false,"children":[{"number":7,"description":"Enter credentials: CC, 999730, 1112","duration":88243,"startTime":"2024-09-04T11:25:07.406-05:00[America/Bogota]","result":"SUCCESS","precondition":false}]},{"number":8,"description":"And selecciono la opcion ingresar","duration":5600,"startTime":"2024-09-04T11:26:35.658-05:00[America/Bogota]","result":"SUCCESS","precondition":false,"children":[{"number":9,"description":"Click on enter option","duration":5592,"startTime":"2024-09-04T11:26:35.664-05:00[America/Bogota]","result":"SUCCESS","precondition":false}]},{"number":10,"description":"Then verifico que me encuentro en el inicio de la app","duration":89593,"startTime":"2024-09-04T11:26:41.259-05:00[America/Bogota]","result":"SUCCESS","precondition":false,"children":[{"number":11,"description":"Verify to be inside the app","duration":89580,"startTime":"2024-09-04T11:26:41.262-05:00[America/Bogota]","result":"SUCCESS","precondition":false}]},{"number":12,"description":"And selecciono la opción \u0027Cambia tu clave\u0027 \"1112\"","duration":13152,"startTime":"2024-09-04T11:28:10.853-05:00[America/Bogota]","result":"SUCCESS","precondition":false,"children":[{"number":13,"description":"Select key change option: 1112","duration":13017,"startTime":"2024-09-04T11:28:10.984-05:00[America/Bogota]","result":"SUCCESS","precondition":false}]},{"number":14,"description":"And creo mi nueva clave Cívica \"1113\"","duration":19182,"startTime":"2024-09-04T11:28:24.006-05:00[America/Bogota]","result":"SUCCESS","precondition":false,"children":[{"number":15,"description":"Create new pass: 1113","duration":19168,"startTime":"2024-09-04T11:28:24.013-05:00[America/Bogota]","result":"SUCCESS","precondition":false}]},{"number":16,"description":"And Cerrar sesion desde el home","duration":57498,"startTime":"2024-09-04T11:28:43.189-05:00[America/Bogota]","result":"SUCCESS","precondition":false,"children":[{"number":17,"description":"Sign out","duration":57485,"startTime":"2024-09-04T11:28:43.199-05:00[America/Bogota]","result":"SUCCESS","precondition":false}]}]}],"userStory":{"id":"cambio-de-clave","storyName":"Cambio de clave","path":"CambioClaveCivica.feature","narrative":"  Escenarios que permiten realizar el cambio de clave","type":"feature"},"featureTag":{"name":"Cambio de clave","type":"feature"},"title":"Cambio_clave_CP0018M_SYS_Realizar el cambio de clave para un usuario BMO.","tags":[{"name":"CambioClaveCivica","type":"tag"},{"name":"Cambio de clave","type":"feature"},{"name":"CP0018M","type":"tag"},{"name":"MUCHAMONEY!","type":"tag"}],"startTime":"2024-09-04T11:23:49.672-05:00[America/Bogota]","duration":354070,"projectKey":"","dataTable":{"headers":["tipoId","usuario","contrasena","newPass","subtipo"],"rows":[{"values":["\"CC\"","\"999730\"","\"1112\"","\"1113\"","\"BMO\""],"result":"SUCCESS"}],"predefinedRows":true,"scenarioOutline":"And ingreso al aplicativo\n\rAnd verifico la version del aplicativo\n\rWhen ingreso las credenciales \u003ctipoId\u003e \u003cusuario\u003e \u003ccontrasena\u003e\n\rAnd selecciono la opcion ingresar\n\rThen verifico que me encuentro en el inicio de la app\n\rAnd selecciono la opción \u0027Cambia tu clave\u0027 \u003ccontrasena\u003e\n\rAnd creo mi nueva clave Cívica \u003cnewPass\u003e\n\rAnd Cerrar sesion desde el home\n\r","dataSetDescriptors":[{"startRow":0,"rowCount":0,"name":""}]},"manual":false,"testSource":"Cucumber","result":"SUCCESS","scenarioOutline":"And ingreso al aplicativo\nAnd verifico la version del aplicativo\nWhen ingreso las credenciales \u003ctipoId\u003e \u003cusuario\u003e \u003ccontrasena\u003e\nAnd selecciono la opcion ingresar\nThen verifico que me encuentro en el inicio de la app\nAnd selecciono la opción \u0027Cambia tu clave\u0027 \u003ccontrasena\u003e\nAnd creo mi nueva clave Cívica \u003cnewPass\u003e\nAnd Cerrar sesion desde el home"}