{"name":"CP0048M_SYS_Realizar un recarga de tarjeta civica exitoso con un usuario MET a un usuario CC.","id":"recargar-tarjeta-cívica;cp0048m-sys-realizar-un-recarga-de-tarjeta-civica-exitoso-con-un-usuario-met-a-un-usuario-cc.","testSteps":[{"number":1,"description":"Example #1: {tipoId\u003d\"CC\", usuario\u003d\"999821\", contrasena\u003d\"1278\", monto\u003d\"2000\", tipoDocumento\u003d\"Cédula de ciudadania\", documento\u003d\"323869\", numCelularUsuario\u003d\"3142045565\", subtipo\u003d\"MET\"}","duration":305354,"startTime":"2023-12-20T11:42:25.398-05:00[America/Bogota]","result":"SUCCESS","precondition":false,"children":[{"number":2,"description":"Given Obtener numero celular actual en redeban \"999821\"","duration":23982,"startTime":"2023-12-20T11:42:30.475-05:00[America/Bogota]","result":"SUCCESS","precondition":false},{"number":3,"description":"And Consultar saldos en redeban","duration":27707,"startTime":"2023-12-20T11:42:54.461-05:00[America/Bogota]","result":"SUCCESS","precondition":false},{"number":4,"description":"And Validar en redeban subtipo \"999821\" \"MET\" \"3142045565\"","duration":6140,"startTime":"2023-12-20T11:43:22.168-05:00[America/Bogota]","result":"SUCCESS","precondition":false},{"number":5,"description":"And Logout redeban","duration":2369,"startTime":"2023-12-20T11:43:28.309-05:00[America/Bogota]","result":"SUCCESS","precondition":false},{"number":6,"description":"And ingreso al aplicativo","duration":5129,"startTime":"2023-12-20T11:43:30.678-05:00[America/Bogota]","result":"SUCCESS","precondition":false,"children":[{"number":7,"description":"Log in to the application","duration":5007,"startTime":"2023-12-20T11:43:30.791-05:00[America/Bogota]","result":"SUCCESS","precondition":false}]},{"number":8,"description":"And verifico la version del aplicativo","duration":6957,"startTime":"2023-12-20T11:43:35.807-05:00[America/Bogota]","result":"SUCCESS","precondition":false,"children":[{"number":9,"description":"Check version","duration":6950,"startTime":"2023-12-20T11:43:35.812-05:00[America/Bogota]","result":"SUCCESS","precondition":false}]},{"number":10,"description":"When ingreso las credenciales \"CC\" \"999821\" \"1278\"","duration":50249,"startTime":"2023-12-20T11:43:42.765-05:00[America/Bogota]","result":"SUCCESS","precondition":false,"children":[{"number":11,"description":"Enter credentials: CC, 999821, 1278","duration":50220,"startTime":"2023-12-20T11:43:42.787-05:00[America/Bogota]","result":"SUCCESS","precondition":false}]},{"number":12,"description":"And selecciono la opcion ingresar","duration":5441,"startTime":"2023-12-20T11:44:33.015-05:00[America/Bogota]","result":"SUCCESS","precondition":false,"children":[{"number":13,"description":"Click on enter option","duration":5434,"startTime":"2023-12-20T11:44:33.021-05:00[America/Bogota]","result":"SUCCESS","precondition":false}]},{"number":14,"description":"And Valido saldos iniciales civica","duration":8168,"startTime":"2023-12-20T11:44:38.456-05:00[America/Bogota]","result":"SUCCESS","precondition":false,"children":[{"number":15,"description":"Validar saldos iniciales civica","duration":8111,"startTime":"2023-12-20T11:44:38.512-05:00[America/Bogota]","result":"SUCCESS","precondition":false}]},{"number":16,"description":"And ingreso al modulo \u0027Tu Tarjeta Civica\u0027 \"Cédula de ciudadania\" \"323869\" \"2000\" \"1278\"","duration":69438,"startTime":"2023-12-20T11:44:46.624-05:00[America/Bogota]","result":"SUCCESS","precondition":false,"children":[{"number":17,"description":"Enter module tu tarjeta civica: Cédula de ciudadania, 323869, 2000, 1278","duration":69413,"startTime":"2023-12-20T11:44:46.642-05:00[America/Bogota]","result":"SUCCESS","precondition":false}]},{"number":18,"description":"Then Validar saldo final civica","duration":7678,"startTime":"2023-12-20T11:45:56.063-05:00[America/Bogota]","result":"SUCCESS","precondition":false,"children":[{"number":19,"description":"Capturar saldos finales civica","duration":7664,"startTime":"2023-12-20T11:45:56.077-05:00[America/Bogota]","result":"SUCCESS","precondition":false}]},{"number":20,"description":"And Cerrar sesion desde el home","duration":27898,"startTime":"2023-12-20T11:46:03.741-05:00[America/Bogota]","result":"SUCCESS","precondition":false,"children":[{"number":21,"description":"Sign out","duration":27895,"startTime":"2023-12-20T11:46:03.744-05:00[America/Bogota]","result":"SUCCESS","precondition":false}]},{"number":22,"description":"And Obtener numero celular actual en redeban \"999821\"","duration":24826,"startTime":"2023-12-20T11:46:31.640-05:00[America/Bogota]","result":"SUCCESS","precondition":false},{"number":23,"description":"And Consultar saldos en redeban","duration":27704,"startTime":"2023-12-20T11:46:56.468-05:00[America/Bogota]","result":"SUCCESS","precondition":false},{"number":24,"description":"And Logout redeban","duration":2629,"startTime":"2023-12-20T11:47:24.175-05:00[America/Bogota]","result":"SUCCESS","precondition":false},{"number":25,"description":"And Validar afectacion de saldos civica","duration":1453,"startTime":"2023-12-20T11:47:26.805-05:00[America/Bogota]","result":"SUCCESS","precondition":false,"children":[{"number":26,"description":"Validar afectacion saldos","duration":1446,"startTime":"2023-12-20T11:47:26.812-05:00[America/Bogota]","result":"SUCCESS","precondition":false}]}]}],"userStory":{"id":"recargar-tarjeta-cívica","storyName":"Recargar tarjeta Cívica","path":"RecargaTarjetaCivica.feature","narrative":"  Escenarios que permiten recargar la tarjeta Cívica","type":"feature"},"featureTag":{"name":"Recargar tarjeta Cívica","type":"feature"},"title":"CP0048M_SYS_Realizar un recarga de tarjeta civica exitoso con un usuario MET a un usuario CC.","tags":[{"name":"Recargar tarjeta cívica","type":"feature"},{"name":"RecargarTarjetaCivica","type":"tag"},{"name":"CP0048M","type":"tag"}],"startTime":"2023-12-20T11:42:25.028-05:00[America/Bogota]","duration":305749,"projectKey":"","dataTable":{"headers":["tipoId","usuario","contrasena","monto","tipoDocumento","documento","numCelularUsuario","subtipo"],"rows":[{"values":["\"CC\"","\"999821\"","\"1278\"","\"2000\"","\"Cédula de ciudadania\"","\"323869\"","\"3142045565\"","\"MET\""],"result":"SUCCESS"}],"predefinedRows":true,"scenarioOutline":"Given Obtener numero celular actual en redeban \u003cusuario\u003e\n\rAnd Consultar saldos en redeban\n\rAnd Validar en redeban subtipo \u003cusuario\u003e \u003csubtipo\u003e \u003cnumCelularUsuario\u003e\n\rAnd Logout redeban\n\rAnd ingreso al aplicativo\n\rAnd verifico la version del aplicativo\n\rWhen ingreso las credenciales \u003ctipoId\u003e \u003cusuario\u003e \u003ccontrasena\u003e\n\rAnd selecciono la opcion ingresar\n\rAnd Valido saldos iniciales civica\n\rAnd ingreso al modulo \u0027Tu Tarjeta Civica\u0027 \u003ctipoDocumento\u003e \u003cdocumento\u003e \u003cmonto\u003e \u003ccontrasena\u003e\n\rThen Validar saldo final civica\n\rAnd Cerrar sesion desde el home\n\rAnd Obtener numero celular actual en redeban \u003cusuario\u003e\n\rAnd Consultar saldos en redeban\n\rAnd Logout redeban\n\rAnd Validar afectacion de saldos civica\n\r","dataSetDescriptors":[{"startRow":0,"rowCount":0,"name":""}]},"manual":false,"testSource":"Cucumber","result":"SUCCESS","scenarioOutline":"Given Obtener numero celular actual en redeban \u003cusuario\u003e\nAnd Consultar saldos en redeban\nAnd Validar en redeban subtipo \u003cusuario\u003e \u003csubtipo\u003e \u003cnumCelularUsuario\u003e\nAnd Logout redeban\nAnd ingreso al aplicativo\nAnd verifico la version del aplicativo\nWhen ingreso las credenciales \u003ctipoId\u003e \u003cusuario\u003e \u003ccontrasena\u003e\nAnd selecciono la opcion ingresar\nAnd Valido saldos iniciales civica\nAnd ingreso al modulo \u0027Tu Tarjeta Civica\u0027 \u003ctipoDocumento\u003e \u003cdocumento\u003e \u003cmonto\u003e \u003ccontrasena\u003e\nThen Validar saldo final civica\nAnd Cerrar sesion desde el home\nAnd Obtener numero celular actual en redeban \u003cusuario\u003e\nAnd Consultar saldos en redeban\nAnd Logout redeban\nAnd Validar afectacion de saldos civica"}