{"name":"Cambio de Clave por olvido - Realizar el cambio de clave para un usuario MET - CC.","id":"cambio-de-clave-por-olvido;cambio-de-clave-por-olvido---realizar-el-cambio-de-clave-para-un-usuario-met---cc.","testSteps":[{"number":1,"description":"Example #1: {tipoId\u003d\"CC\", usuario\u003d\"10305051\", contrasena\u003d\"1431\", newPass\u003d\"1432\", correo\u003d\"pruebaslabcivi@gmail.com\", correoErroneo\u003d\"xxx@gmail.com\"}","duration":62242,"startTime":"2023-12-05T12:34:01.881-05:00[America/Bogota]","exception":{"errorType":"java.lang.AssertionError","message":"No pudo interactuar con el elemento: //XCUIElementTypeButton[@name\u003d\"Aceptar\"]","stackTrace":[{"declaringClass":"daviplata.nacional.iOS.utilidades.UtilidadesTCS","methodName":"clicElement","fileName":"UtilidadesTCS.java","lineNumber":216},{"declaringClass":"daviplata.nacional.iOS.steps.CambioClaveOlvidoSteps","methodName":"confirmBadEmail","fileName":"CambioClaveOlvidoSteps.java","lineNumber":49},{"declaringClass":"daviplata.nacional.iOS.definitions.CambioClaveOlvidoDefinitions","methodName":"ingresoCorreoErroneoYValidoMensajeError","fileName":"CambioClaveOlvidoDefinitions.java","lineNumber":40},{"declaringClass":"✽","methodName":"ingreso correo erróneo y valido mensaje error \"xxx@gmail.com\" \"1432\" \"CC\" \"10305051\"","fileName":"src/test/resources/features/CambioClaveOlvido.feature","lineNumber":11}]},"result":"FAILURE","precondition":false,"children":[{"number":2,"description":"Given ingreso al aplicativo","duration":4510,"startTime":"2023-12-05T12:34:06.388-05:00[America/Bogota]","result":"SUCCESS","precondition":false,"children":[{"number":3,"description":"Log in to the application","duration":4170,"startTime":"2023-12-05T12:34:06.711-05:00[America/Bogota]","result":"SUCCESS","precondition":false}]},{"number":4,"description":"And verifico la version del aplicativo","duration":6464,"startTime":"2023-12-05T12:34:10.900-05:00[America/Bogota]","result":"SUCCESS","precondition":false,"children":[{"number":5,"description":"Check version","duration":6443,"startTime":"2023-12-05T12:34:10.916-05:00[America/Bogota]","result":"SUCCESS","precondition":false}]},{"number":6,"description":"And ingreso al módulo \u0027Olvidaste tu clave\u0027 \"CC\" \"10305051\"","duration":11710,"startTime":"2023-12-05T12:34:17.365-05:00[America/Bogota]","result":"SUCCESS","precondition":false,"children":[{"number":7,"description":"Forgot pass option: CC, 10305051","duration":11619,"startTime":"2023-12-05T12:34:17.455-05:00[America/Bogota]","result":"SUCCESS","precondition":false}]},{"number":8,"description":"And ingreso correo erróneo y valido mensaje error \"xxx@gmail.com\" \"1432\" \"CC\" \"10305051\"","duration":31054,"startTime":"2023-12-05T12:34:29.076-05:00[America/Bogota]","exception":{"errorType":"java.lang.AssertionError","message":"No pudo interactuar con el elemento: //XCUIElementTypeButton[@name\u003d\"Aceptar\"]","stackTrace":[{"declaringClass":"daviplata.nacional.iOS.utilidades.UtilidadesTCS","methodName":"clicElement","fileName":"UtilidadesTCS.java","lineNumber":216},{"declaringClass":"daviplata.nacional.iOS.steps.CambioClaveOlvidoSteps","methodName":"confirmBadEmail","fileName":"CambioClaveOlvidoSteps.java","lineNumber":49},{"declaringClass":"daviplata.nacional.iOS.definitions.CambioClaveOlvidoDefinitions","methodName":"ingresoCorreoErroneoYValidoMensajeError","fileName":"CambioClaveOlvidoDefinitions.java","lineNumber":40},{"declaringClass":"✽","methodName":"ingreso correo erróneo y valido mensaje error \"xxx@gmail.com\" \"1432\" \"CC\" \"10305051\"","fileName":"src/test/resources/features/CambioClaveOlvido.feature","lineNumber":11}]},"result":"FAILURE","precondition":false,"children":[{"number":9,"description":"Confirm bad email: xxx@gmail.com, 1432, CC, 10305051","duration":31041,"startTime":"2023-12-05T12:34:29.081-05:00[America/Bogota]","exception":{"errorType":"java.lang.AssertionError","message":"No pudo interactuar con el elemento: //XCUIElementTypeButton[@name\u003d\"Aceptar\"]","stackTrace":[{"declaringClass":"daviplata.nacional.iOS.utilidades.UtilidadesTCS","methodName":"clicElement","fileName":"UtilidadesTCS.java","lineNumber":216},{"declaringClass":"daviplata.nacional.iOS.steps.CambioClaveOlvidoSteps","methodName":"confirmBadEmail","fileName":"CambioClaveOlvidoSteps.java","lineNumber":49},{"declaringClass":"daviplata.nacional.iOS.definitions.CambioClaveOlvidoDefinitions","methodName":"ingresoCorreoErroneoYValidoMensajeError","fileName":"CambioClaveOlvidoDefinitions.java","lineNumber":40},{"declaringClass":"cucumber.runner.Runner","methodName":"runPickle","fileName":"Runner.java","lineNumber":80},{"declaringClass":"daviplata.nacional.iOS.runners.RunnerPersonalizado","methodName":"run","fileName":"RunnerPersonalizado.java","lineNumber":63},{"declaringClass":"org.eclipse.jdt.internal.junit4.runner.JUnit4TestReference","methodName":"run","fileName":"JUnit4TestReference.java","lineNumber":93},{"declaringClass":"org.eclipse.jdt.internal.junit.runner.TestExecution","methodName":"run","fileName":"TestExecution.java","lineNumber":40},{"declaringClass":"org.eclipse.jdt.internal.junit.runner.RemoteTestRunner","methodName":"runTests","fileName":"RemoteTestRunner.java","lineNumber":529},{"declaringClass":"org.eclipse.jdt.internal.junit.runner.RemoteTestRunner","methodName":"runTests","fileName":"RemoteTestRunner.java","lineNumber":756},{"declaringClass":"org.eclipse.jdt.internal.junit.runner.RemoteTestRunner","methodName":"run","fileName":"RemoteTestRunner.java","lineNumber":452},{"declaringClass":"org.eclipse.jdt.internal.junit.runner.RemoteTestRunner","methodName":"main","fileName":"RemoteTestRunner.java","lineNumber":210}]},"result":"FAILURE","precondition":false}]},{"number":10,"description":"And confirmo correo electrónico y creo clave \"pruebaslabcivi@gmail.com\" \"1432\"","duration":2,"startTime":"2023-12-05T12:35:00.130-05:00[America/Bogota]","result":"SKIPPED","precondition":false}]}],"userStory":{"id":"cambio-de-clave-por-olvido","storyName":"Cambio de clave por olvido","path":"CambioClaveOlvido.feature","narrative":"  Escenarios que permiten realizar el cambio de clave por olvido","type":"feature"},"featureTag":{"name":"Cambio de clave por olvido","type":"feature"},"title":"Cambio de Clave por olvido - Realizar el cambio de clave para un usuario MET - CC.","tags":[{"name":"CambioClaveOlvido001","type":"tag"},{"name":"Cambio de clave por olvido","type":"feature"},{"name":"CambioClaveOlvido","type":"tag"}],"startTime":"2023-12-05T12:34:01.392-05:00[America/Bogota]","duration":62732,"testFailureCause":{"errorType":"java.lang.AssertionError","message":"No pudo interactuar con el elemento: //XCUIElementTypeButton[@name\u003d\"Aceptar\"]","stackTrace":[{"declaringClass":"daviplata.nacional.iOS.utilidades.UtilidadesTCS","methodName":"clicElement","fileName":"UtilidadesTCS.java","lineNumber":216},{"declaringClass":"daviplata.nacional.iOS.steps.CambioClaveOlvidoSteps","methodName":"confirmBadEmail","fileName":"CambioClaveOlvidoSteps.java","lineNumber":49},{"declaringClass":"daviplata.nacional.iOS.definitions.CambioClaveOlvidoDefinitions","methodName":"ingresoCorreoErroneoYValidoMensajeError","fileName":"CambioClaveOlvidoDefinitions.java","lineNumber":40},{"declaringClass":"cucumber.runner.Runner","methodName":"runPickle","fileName":"Runner.java","lineNumber":80},{"declaringClass":"daviplata.nacional.iOS.runners.RunnerPersonalizado","methodName":"run","fileName":"RunnerPersonalizado.java","lineNumber":63},{"declaringClass":"org.eclipse.jdt.internal.junit4.runner.JUnit4TestReference","methodName":"run","fileName":"JUnit4TestReference.java","lineNumber":93},{"declaringClass":"org.eclipse.jdt.internal.junit.runner.TestExecution","methodName":"run","fileName":"TestExecution.java","lineNumber":40},{"declaringClass":"org.eclipse.jdt.internal.junit.runner.RemoteTestRunner","methodName":"runTests","fileName":"RemoteTestRunner.java","lineNumber":529},{"declaringClass":"org.eclipse.jdt.internal.junit.runner.RemoteTestRunner","methodName":"runTests","fileName":"RemoteTestRunner.java","lineNumber":756},{"declaringClass":"org.eclipse.jdt.internal.junit.runner.RemoteTestRunner","methodName":"run","fileName":"RemoteTestRunner.java","lineNumber":452},{"declaringClass":"org.eclipse.jdt.internal.junit.runner.RemoteTestRunner","methodName":"main","fileName":"RemoteTestRunner.java","lineNumber":210}]},"testFailureClassname":"java.lang.AssertionError","testFailureMessage":"No pudo interactuar con el elemento: //XCUIElementTypeButton[@name\u003d\"Aceptar\"]","testFailureSummary":"FAILURE;java.lang.AssertionError;No pudo interactuar con el elemento: //XCUIElementTypeButton[@name\u003d\"Aceptar\"];UtilidadesTCS.java","projectKey":"","annotatedResult":"FAILURE","dataTable":{"headers":["tipoId","usuario","contrasena","newPass","correo","correoErroneo"],"rows":[{"values":["\"CC\"","\"10305051\"","\"1431\"","\"1432\"","\"pruebaslabcivi@gmail.com\"","\"xxx@gmail.com\""],"result":"FAILURE"}],"predefinedRows":true,"scenarioOutline":"Given ingreso al aplicativo\n\rAnd verifico la version del aplicativo\n\rAnd ingreso al módulo \u0027Olvidaste tu clave\u0027 \u003ctipoId\u003e \u003cusuario\u003e\n\rAnd ingreso correo erróneo y valido mensaje error \u003ccorreoErroneo\u003e \u003cnewPass\u003e \u003ctipoId\u003e \u003cusuario\u003e\n\rAnd confirmo correo electrónico y creo clave \u003ccorreo\u003e \u003cnewPass\u003e\n\r","dataSetDescriptors":[{"startRow":0,"rowCount":0,"name":""}]},"manual":false,"testSource":"Cucumber","result":"FAILURE","scenarioOutline":"Given ingreso al aplicativo\nAnd verifico la version del aplicativo\nAnd ingreso al módulo \u0027Olvidaste tu clave\u0027 \u003ctipoId\u003e \u003cusuario\u003e\nAnd ingreso correo erróneo y valido mensaje error \u003ccorreoErroneo\u003e \u003cnewPass\u003e \u003ctipoId\u003e \u003cusuario\u003e\nAnd confirmo correo electrónico y creo clave \u003ccorreo\u003e \u003cnewPass\u003e"}